hypermodern_guyhoozdis/__init__.py
hypermodern_guyhoozdis/__main__.py
hypermodern_guyhoozdis/console.py
hypermodern_guyhoozdis/wikipedia.py
hypermodern_guyhoozdis-0.7.0.dist-info/LICENSE
hypermodern_guyhoozdis-0.7.0.dist-info/METADATA
hypermodern_guyhoozdis-0.7.0.dist-info/WHEEL
hypermodern_guyhoozdis-0.7.0.dist-info/entry_points.txt
hypermodern_guyhoozdis-0.7.0.dist-info/RECORD
