Metadata-Version: 2.1
Name: hypermodern-guyhoozdis
Version: 0.7.0
Summary: A template package based on The Hypermodern Project
Home-page: https://github.com/guyhoozdis/hypermodern-python
License: MIT
Keywords: hypermodern,template,package,guyhoozdis
Author: Guy Hoozdis
Author-email: GuyHoozdis@users.noreply.github.com
Requires-Python: >=3.8.1,<3.13
Classifier: License :: OSI Approved :: MIT License
Classifier: Programming Language :: Python :: 3
Classifier: Programming Language :: Python :: 3.9
Classifier: Programming Language :: Python :: 3.10
Classifier: Programming Language :: Python :: 3.11
Classifier: Programming Language :: Python :: 3.12
Requires-Dist: click (>=8.1.7,<9.0.0)
Requires-Dist: desert (>=2022.9.22,<2023.0.0)
Requires-Dist: marshmallow (>=3.21.3,<4.0.0)
Requires-Dist: requests (>=2.32.3,<3.0.0)
Project-URL: Documentation, https://hypermodern-guyhoozdis.readthedocs.io
Project-URL: Repository, https://github.com/guyhoozdis/hypermodern-python
